D_FF.v
// EE271 Assignent 8  - NOTE - ALL Clear & Preset are active low functionality

//********************************	D-FF using behavioral	*************************************************************

module DFFBehavior(q,d,clk,clear,preset);
  
  output q;
  input d,clk,clear,preset;
  reg q;

always @(posedge clk)
	begin
		if(clear == 0 && preset == 0)
		q <= 1'b0;
	
		if(clear == 0 && preset == 1)
		q <= 1'b0;
		
		else if(clear == 1 && preset == 0)
		q <= 1'b1;
		
		else
		q <= d;
	end;

always @(negedge clk)
	begin
		if(clear == 0 && preset == 0)
		q <= 1'b0;
	
		if(clear == 0 && preset == 1)
		q <= 1'b0;
		
		else if(clear == 1 && preset == 0)
		q <= 1'b1;
		
		else
		q <= q;	
	end;
endmodule

//********************************	D-FF using Behavioral Simulation	*************************************************************

module D_FF_Behavior_Simulation;

  wire q;
  reg d,clk,clear,preset;
  reg q,clk;


DFFBehavior Inst1(q,d,clk,clear,preset);

initial begin
   $dumpfile ("waveform.vcd");
   $dumpvars (0);
   
	clk = 1'b0; 	
	forever	#10 clk = ~clk;
 $finish;
end

 initial begin

	$monitor($time," d=%b , clk=%b, clear=%b, preset=%b q=%b ", d,clk,clear,preset,q);

	#10; //clk=1 #10 Make changes here
	d = 1'b0;	clear = 1'b1;   preset = 1'b0;
	
	#10;	d = 1'b1;	clear = 1'b1;	preset = 1'b0;
	
	#10; //clk=1 #30 Make changes here
	d = 1'b0;	clear = 1'b1;	preset = 1'b1;
	
	#10; 
	d = 1'bx;	clear = 1'b0;	preset = 1'b0;

	#10; //clk=1 #50 Make changes here
	d = 1'b0;	clear = 1'b1;	preset = 1'b0;
	
	#10; 
	d = 1'b1;	clear = 1'b0;	preset = 1'b1;

	#10; //clk=1 #70 Make changes here
	d = 1'b1;	clear = 1'b1;	preset = 1'b1;

	#10;
 $finish;
 end  
endmodule

//*****************************************************

waveform.vcd
$date
	Sat Jan 27 19:34:00 2018
$end

$version
	Synopsys VCS version I-2014.03-2
$end

$timescale
	1s
$end

$comment Csum: 1 6fbff9d499b03237 $end


$scope module D_FF_Behavior_Simulation $end
$var wire 1 ! q $end
$var reg 1 " d $end
$var reg 1 # clk $end
$var reg 1 $ clear $end
$var reg 1 % preset $end

$scope module Inst1 $end
$var reg 1 & q $end
$var wire 1 " d $end
$var wire 1 # clk $end
$var wire 1 $ clear $end
$var wire 1 % preset $end
$upscope $end

$upscope $end

$enddefinitions $end

#0
$dumpvars
x&
x$
0#
x"
x%
x!
$end
#10
1#
0"
1$
0%
1&
1!
#20
0#
1"
#30
1#
0"
1%
0&
0!
#40
0#
x"
0$
0%
#50
1#
0"
1$
1&
1!
#60
0#
1"
0$
1%
0&
0!
#70
1#
1$
1&
1!
